live_inspect/__init__.py
live_inspect/config.py
live_inspect/uiautomation.py
live_inspect/watch_cursor.py
live_inspect/__pycache__/__init__.cpython-313.pyc
live_inspect/__pycache__/config.cpython-313.pyc
live_inspect/__pycache__/uiautomation.cpython-313.pyc
live_inspect/__pycache__/watch_cursor.cpython-313.pyc
live_inspect/bin/FlaUI.Core.dll
live_inspect/bin/FlaUI.UIA2.dll
live_inspect/bin/FlaUI.UIA3.dll
live_inspect/bin/Interop.UIAutomationClient.dll
live_inspect-0.1.2.dist-info/licenses/LICENSE
live_inspect-0.1.2.dist-info/METADATA
live_inspect-0.1.2.dist-info/WHEEL
live_inspect-0.1.2.dist-info/top_level.txt
live_inspect-0.1.2.dist-info/RECORD
