Metadata-Version: 2.4
Name: live-inspect
Version: 0.1.2
Summary: To live inspect the UI elements on windows.
Requires-Python: >=3.13
License-File: LICENSE
Requires-Dist: clr>=1.0.3
Requires-Dist: pythonnet>=3.0.5
Dynamic: license-file
